common/__init__.py
common/decos.py
common/descryptors.py
common/errors.py
common/log_decorator.py
common/metaclasses.py
common/utils.py
common/variables.py
logs/__init__.py
logs/config_client_log.py
logs/config_server_log.py
server/__init__.py
server/add_user.py
server/config_window.py
server/core.py
server/main_window.py
server/remove_user.py
server/server_db.py
server/stat_window.py
unit_tests/__init__.py
unit_tests/test_client.py
unit_tests/test_server.py
unit_tests/test_utils.py
messanger_lite_server-1.0.1.dist-info/LICENSE.txt
messanger_lite_server-1.0.1.dist-info/METADATA
messanger_lite_server-1.0.1.dist-info/WHEEL
messanger_lite_server-1.0.1.dist-info/top_level.txt
messanger_lite_server-1.0.1.dist-info/RECORD
